{
  "project_info": {
    "project_number": "332265682357",
    "firebase_url": "https://listatarefasflutter-default-rtdb.firebaseio.com",
    "project_id": "listatarefasflutter",
    "storage_bucket": "listatarefasflutter.appspot.com"
  },
  "client": [
    {
      "client_info": {
        "mobilesdk_app_id": "1:332265682357:android:4cb0a867559902711355fc",
        "android_client_info": {
          "package_name": "br.com.adrimatec.projeto_lista_de_tarefas"
        }
      },
      "oauth_client": [
        {
          "client_id": "332265682357-90e57230dftfost52ampamgpvj0mfsg6.apps.googleusercontent.com",
          "client_type": 3
        }
      ],
      "api_key": [
        {
          "current_key": "AIzaSyAh033s33S-_AAcaGXBTzoO33FXyU1fr7k"
        }
      ],
      "services": {
        "appinvite_service": {
          "other_platform_oauth_client": [
            {
              "client_id": "332265682357-90e57230dftfost52ampamgpvj0mfsg6.apps.googleusercontent.com",
              "client_type": 3
            }
          ]
        }
      }
    }
  ],
  "configuration_version": "1"
}